Metadata-Version: 1.0
Name: mylibtest
Version: 0.1.1
Summary: A line of description
Home-page: https://upload.pypi.org/legacy/mylibtest_v011/
Author: shrawan shinde
Author-email: syntaxerror1972@gmail.com
License: MIT
Platform: UNKNOWN
